corona.py
coronapy.py
coronapy-0.1.6.dist-info/METADATA
coronapy-0.1.6.dist-info/WHEEL
coronapy-0.1.6.dist-info/top_level.txt
coronapy-0.1.6.dist-info/RECORD
