Metadata-Version: 2.1
Name: coronapy
Version: 0.1.6
Summary: UNKNOWN
Home-page: https://github.com/SylvainGuieu/corona
Author: Sylvain Guieu
Author-email: sylvain.guieu@univ-grenoble-alpes.fr
License: Creative Commons Attribution-Noncommercial-Share Alike license
Platform: UNKNOWN
Requires-Dist: pandas
Requires-Dist: matplotlib
